{"registryId":"registry.banking-products.v1","version":"1.0.0-design","productionAuthorized":false,"products":[{"id":"banking-product.basic-transaction-account.v1","name":"Basic Transaction Account","productType":"transaction","riskBand":"low","accessPolicy":"no-credit","availability":"country-policy-and-capability-dependent","pricingPolicy":"rates-fees-and-limits-unapproved-until-affordability-simulation","disclosureRequirements":["total-cost-band","liquidity-or-lockup","missed-payment-or-default-treatment","recovery-and-appeal-path"],"prohibitedBehavior":["hidden-fees","guaranteed-profit-language","automatic-cross-game-ownership","direct-unreviewed-ledger-write"],"recoveryPath":"fee-review-and-account-transfer","displayOrder":1,"runtimeSupport":"definition-only","activationAuthorized":false},{"id":"banking-product.protected-savings-account.v1","name":"Protected Savings Account","productType":"savings","riskBand":"low","accessPolicy":"no-credit","availability":"country-policy-and-capability-dependent","pricingPolicy":"rates-fees-and-limits-unapproved-until-affordability-simulation","disclosureRequirements":["total-cost-band","liquidity-or-lockup","missed-payment-or-default-treatment","recovery-and-appeal-path"],"prohibitedBehavior":["hidden-fees","guaranteed-profit-language","automatic-cross-game-ownership","direct-unreviewed-ledger-write"],"recoveryPath":"fee-review-and-account-transfer","displayOrder":2,"runtimeSupport":"definition-only","activationAuthorized":false},{"id":"banking-product.emergency-reserve-account.v1","name":"Emergency Reserve Account","productType":"savings","riskBand":"low","accessPolicy":"restricted-withdrawal","availability":"country-policy-and-capability-dependent","pricingPolicy":"rates-fees-and-limits-unapproved-until-affordability-simulation","disclosureRequirements":["total-cost-band","liquidity-or-lockup","missed-payment-or-default-treatment","recovery-and-appeal-path"],"prohibitedBehavior":["hidden-fees","guaranteed-profit-language","automatic-cross-game-ownership","direct-unreviewed-ledger-write"],"recoveryPath":"fee-review-and-account-transfer","displayOrder":3,"runtimeSupport":"definition-only","activationAuthorized":false},{"id":"banking-product.fixed-term-deposit.v1","name":"Fixed-Term Deposit","productType":"deposit","riskBand":"low-moderate","accessPolicy":"liquidity-tradeoff","availability":"country-policy-and-capability-dependent","pricingPolicy":"rates-fees-and-limits-unapproved-until-affordability-simulation","disclosureRequirements":["total-cost-band","liquidity-or-lockup","missed-payment-or-default-treatment","recovery-and-appeal-path"],"prohibitedBehavior":["hidden-fees","guaranteed-profit-language","automatic-cross-game-ownership","direct-unreviewed-ledger-write"],"recoveryPath":"fee-review-and-account-transfer","displayOrder":4,"runtimeSupport":"definition-only","activationAuthorized":false},{"id":"banking-product.credit-builder-line.v1","name":"Credit Builder Line","productType":"credit","riskBand":"moderate","accessPolicy":"small-secured-limit","availability":"country-policy-and-capability-dependent","pricingPolicy":"rates-fees-and-limits-unapproved-until-affordability-simulation","disclosureRequirements":["total-cost-band","liquidity-or-lockup","missed-payment-or-default-treatment","recovery-and-appeal-path"],"prohibitedBehavior":["hidden-fees","guaranteed-profit-language","automatic-cross-game-ownership","direct-unreviewed-ledger-write"],"recoveryPath":"hardship-review-restructure-or-supervised-exit","displayOrder":5,"runtimeSupport":"definition-only","activationAuthorized":false},{"id":"banking-product.education-and-training-loan.v1","name":"Education and Training Loan","productType":"credit","riskBand":"moderate","accessPolicy":"verified-program-only","availability":"country-policy-and-capability-dependent","pricingPolicy":"rates-fees-and-limits-unapproved-until-affordability-simulation","disclosureRequirements":["total-cost-band","liquidity-or-lockup","missed-payment-or-default-treatment","recovery-and-appeal-path"],"prohibitedBehavior":["hidden-fees","guaranteed-profit-language","automatic-cross-game-ownership","direct-unreviewed-ledger-write"],"recoveryPath":"hardship-review-restructure-or-supervised-exit","displayOrder":6,"runtimeSupport":"definition-only","activationAuthorized":false},{"id":"banking-product.equipment-finance-plan.v1","name":"Equipment Finance Plan","productType":"credit","riskBand":"moderate-high","accessPolicy":"asset-linked","availability":"country-policy-and-capability-dependent","pricingPolicy":"rates-fees-and-limits-unapproved-until-affordability-simulation","disclosureRequirements":["total-cost-band","liquidity-or-lockup","missed-payment-or-default-treatment","recovery-and-appeal-path"],"prohibitedBehavior":["hidden-fees","guaranteed-profit-language","automatic-cross-game-ownership","direct-unreviewed-ledger-write"],"recoveryPath":"hardship-review-restructure-or-supervised-exit","displayOrder":7,"runtimeSupport":"definition-only","activationAuthorized":false},{"id":"banking-product.small-business-operating-account.v1","name":"Small Business Operating Account","productType":"business","riskBand":"moderate","accessPolicy":"cash-management","availability":"country-policy-and-capability-dependent","pricingPolicy":"rates-fees-and-limits-unapproved-until-affordability-simulation","disclosureRequirements":["total-cost-band","liquidity-or-lockup","missed-payment-or-default-treatment","recovery-and-appeal-path"],"prohibitedBehavior":["hidden-fees","guaranteed-profit-language","automatic-cross-game-ownership","direct-unreviewed-ledger-write"],"recoveryPath":"fee-review-and-account-transfer","displayOrder":8,"runtimeSupport":"definition-only","activationAuthorized":false},{"id":"banking-product.trade-settlement-facility.v1","name":"Trade Settlement Facility","productType":"trade-finance","riskBand":"high","accessPolicy":"verified-contract-only","availability":"country-policy-and-capability-dependent","pricingPolicy":"rates-fees-and-limits-unapproved-until-affordability-simulation","disclosureRequirements":["total-cost-band","liquidity-or-lockup","missed-payment-or-default-treatment","recovery-and-appeal-path"],"prohibitedBehavior":["hidden-fees","guaranteed-profit-language","automatic-cross-game-ownership","direct-unreviewed-ledger-write"],"recoveryPath":"hardship-review-restructure-or-supervised-exit","displayOrder":9,"runtimeSupport":"definition-only","activationAuthorized":false},{"id":"banking-product.recovery-restructure-plan.v1","name":"Recovery Restructure Plan","productType":"recovery","riskBand":"moderate","accessPolicy":"hardship-review","availability":"country-policy-and-capability-dependent","pricingPolicy":"rates-fees-and-limits-unapproved-until-affordability-simulation","disclosureRequirements":["total-cost-band","liquidity-or-lockup","missed-payment-or-default-treatment","recovery-and-appeal-path"],"prohibitedBehavior":["hidden-fees","guaranteed-profit-language","automatic-cross-game-ownership","direct-unreviewed-ledger-write"],"recoveryPath":"fee-review-and-account-transfer","displayOrder":10,"runtimeSupport":"definition-only","activationAuthorized":false}]}
